deepvelo/__init__.py
deepvelo/base/__init__.py
deepvelo/base/base_data_loader.py
deepvelo/base/base_model.py
deepvelo/base/base_trainer.py
deepvelo/data_loader/data_loaders.py
deepvelo/logger/__init__.py
deepvelo/logger/logger.py
deepvelo/logger/logger_config.json
deepvelo/logger/visualization.py
deepvelo/model/layers.py
deepvelo/model/loss.py
deepvelo/model/metric.py
deepvelo/model/model.py
deepvelo/parse_config.py
deepvelo/pipeline/__init__.py
deepvelo/pipeline/eval.py
deepvelo/plot/__init__.py
deepvelo/plot/plot.py
deepvelo/plot/scatter.py
deepvelo/tool/__init__.py
deepvelo/tool/driver_gene.py
deepvelo/tool/kinetic_rates.py
deepvelo/tool/stats.py
deepvelo/tool/velocity.py
deepvelo/train.py
deepvelo/trainer/__init__.py
deepvelo/trainer/trainer.py
deepvelo/utils/__init__.py
deepvelo/utils/confidence.py
deepvelo/utils/map_velocity_expression.py
deepvelo/utils/optimization.py
deepvelo/utils/plot.py
deepvelo/utils/preprocess.py
deepvelo/utils/scatter.py
deepvelo/utils/temporal.py
deepvelo/utils/util.py
deepvelo-0.2.8.dist-info/LICENSE
deepvelo-0.2.8.dist-info/WHEEL
deepvelo-0.2.8.dist-info/METADATA
deepvelo-0.2.8.dist-info/RECORD
