Metadata-Version: 2.1
Name: deepvelo
Version: 0.2.8
Summary: Deep Velocity
Home-page: https://github.com/bowang-lab/DeepVelo
License: MIT
Author: subercui
Author-email: subercui@gmail.com
Requires-Python: >=3.7.1,<3.10
Classifier: License :: OSI Approved :: MIT License
Classifier: Programming Language :: Python :: 3
Classifier: Programming Language :: Python :: 3.8
Classifier: Programming Language :: Python :: 3.9
Provides-Extra: cellrank
Provides-Extra: gpu
Requires-Dist: adjustText (>=0.7.3,<0.8.0)
Requires-Dist: dgl (>=0.4,!=0.8.0.post1,<0.9); extra != "gpu"
Requires-Dist: dgl-cu102 (>=0.4,!=0.8.0.post1,<0.9); extra == "gpu"
Requires-Dist: hnswlib (>=0.6.2,<0.7.0)
Requires-Dist: igraph (>=0.9.10,<0.10.0)
Requires-Dist: matplotlib (>=3.3,<3.6)
Requires-Dist: numpy (>=1.21.1,<2.0.0)
Requires-Dist: scanpy (>=1.8.2,<2.0.0)
Requires-Dist: scvelo (>=0.2.4,<0.3.0)
Requires-Dist: seaborn (>=0.11.2,<0.12.0)
Requires-Dist: torch (>=1.2,<1.13)
Requires-Dist: tqdm (>=4.62.3,<5.0.0)
Requires-Dist: umap-learn (>=0.5.2,<=0.5.4)
Project-URL: Repository, https://github.com/bowang-lab/DeepVelo
